README.rst
setup.py
livechart/__init__.py
livechart/chart.py
livechart/script.py
livechart.egg-info/PKG-INFO
livechart.egg-info/SOURCES.txt
livechart.egg-info/dependency_links.txt
livechart.egg-info/entry_points.txt
livechart.egg-info/requires.txt
livechart.egg-info/top_level.txt