Metadata-Version: 1.0
Name: livechart
Version: 0.0.4
Summary: A CLI utility for charting data on the fly.
Home-page: https://github.com/sevko/livechart
Author: Severyn Kozak
Author-email: severyn.kozak@gmail.com
License: MIT
Platform: UNKNOWN
